[
  {
    "name": "军武森林公园",
    "name_en": "Junwu Forest Park",
    "latitude": 23.85,
    "longitude": 107.52,
    "province": "广西",
    "province_en": "Guangxi",
    "habitat": "subtropical_broadleaf_forest",
    "elevation_m": 450,
    "notes": "Key monitoring site for Gorsachius magnificus. 12 breeding pairs documented (2013-2024).",
    "target_species": ["Gorsachius magnificus"],
    "active": true
  },
  {
    "name": "弄岗国家级自然保护区",
    "name_en": "Nonggang National Nature Reserve",
    "latitude": 22.47,
    "longitude": 107.04,
    "province": "广西",
    "province_en": "Guangxi",
    "habitat": "tropical_limestone_karst_forest",
    "elevation_m": 300,
    "notes": "UNESCO Biosphere Reserve. Rich avifauna including multiple threatened species in limestone karst habitat.",
    "target_species": ["Gorsachius magnificus", "Polyplectron katsumatae"],
    "active": true
  },
  {
    "name": "大明山国家级自然保护区",
    "name_en": "Daming Mountain National Nature Reserve",
    "latitude": 23.50,
    "longitude": 108.38,
    "province": "广西",
    "province_en": "Guangxi",
    "habitat": "montane_evergreen_forest",
    "elevation_m": 1200,
    "notes": "Highest peak in southern Guangxi. Important site for montane forest bird species and amphibians.",
    "target_species": ["Gorsachius magnificus", "Tragopan caboti"],
    "active": true
  },
  {
    "name": "十万大山国家级自然保护区",
    "name_en": "Shiwandashan National Nature Reserve",
    "latitude": 21.90,
    "longitude": 107.90,
    "province": "广西",
    "province_en": "Guangxi",
    "habitat": "subtropical_evergreen_forest",
    "elevation_m": 600,
    "notes": "Rich lowland-montane transition zone. Historical records of White-eared Night Heron.",
    "target_species": ["Gorsachius magnificus"],
    "active": true
  },
  {
    "name": "南岭国家级自然保护区",
    "name_en": "Nanling National Nature Reserve",
    "latitude": 24.93,
    "longitude": 112.89,
    "province": "广东",
    "province_en": "Guangdong",
    "habitat": "subtropical_broadleaf_forest",
    "elevation_m": 800,
    "notes": "Important site for bird surveys along the Nanling mountain range. Multiple heron species recorded.",
    "target_species": ["Gorsachius magnificus"],
    "active": true
  },
  {
    "name": "鹅凰嶂省级自然保护区",
    "name_en": "Ehuangzhang Provincial Nature Reserve",
    "latitude": 22.05,
    "longitude": 110.97,
    "province": "广东",
    "province_en": "Guangdong",
    "habitat": "subtropical_monsoon_forest",
    "elevation_m": 350,
    "notes": "Known breeding site for White-eared Night Heron in Guangdong province.",
    "target_species": ["Gorsachius magnificus"],
    "active": true
  },
  {
    "name": "井冈山国家级自然保护区",
    "name_en": "Jinggangshan National Nature Reserve",
    "latitude": 26.58,
    "longitude": 114.17,
    "province": "江西",
    "province_en": "Jiangxi",
    "habitat": "subtropical_evergreen_forest",
    "elevation_m": 900,
    "notes": "Confirmed records of White-eared Night Heron. Important site in eastern range.",
    "target_species": ["Gorsachius magnificus", "Tragopan caboti"],
    "active": true
  },
  {
    "name": "武夷山国家公园",
    "name_en": "Wuyi Mountains National Park",
    "latitude": 27.73,
    "longitude": 117.67,
    "province": "福建",
    "province_en": "Fujian",
    "habitat": "subtropical_broadleaf_forest",
    "elevation_m": 750,
    "notes": "UNESCO World Heritage Site. Records of White-eared Night Heron in the park's stream valleys.",
    "target_species": ["Gorsachius magnificus"],
    "active": true
  },
  {
    "name": "海南热带雨林国家公园",
    "name_en": "Hainan Tropical Rainforest National Park",
    "latitude": 19.05,
    "longitude": 109.68,
    "province": "海南",
    "province_en": "Hainan",
    "habitat": "tropical_montane_rainforest",
    "elevation_m": 600,
    "notes": "Home to Hainan Gibbon. Historical records of White-eared Night Heron; needs verification.",
    "target_species": ["Gorsachius magnificus", "Nomascus hainanus"],
    "active": true
  },
  {
    "name": "八大公山国家级自然保护区",
    "name_en": "Badagongshan National Nature Reserve",
    "latitude": 29.77,
    "longitude": 110.10,
    "province": "湖南",
    "province_en": "Hunan",
    "habitat": "subtropical_montane_forest",
    "elevation_m": 1100,
    "notes": "Northernmost confirmed population of White-eared Night Heron in recent surveys.",
    "target_species": ["Gorsachius magnificus"],
    "active": true
  }
]
